file_verifier/__init__.py
file_verifier/constants.py
file_verifier/error.py
file_verifier/file_validator.py
file_verifier/convertor/__init__.py
file_verifier/mime/__init__.py
file_verifier/size/__init__.py
file_verifier/type/__init__.py
file_verifier-0.0.0.dist-info/LICENSE.txt
file_verifier-0.0.0.dist-info/METADATA
file_verifier-0.0.0.dist-info/WHEEL
file_verifier-0.0.0.dist-info/top_level.txt
file_verifier-0.0.0.dist-info/RECORD
