Metadata-Version: 2.1
Name: file-verifier
Version: 0.0.0
Summary: Validation for local and upload file
Author-email: Dao Quang Duy <duydaoquang12@gmail.com>
Maintainer-email: Rabiloo Developers <oss@rabiloo.com>
License: The MIT License
Project-URL: Homepage, https://github.com/rabiloo/python-file-verifier
Project-URL: Repository, https://github.com/rabiloo/python-file-verifier
Project-URL: Bug Tracker, https://github.com/rabiloo/python-file-verifier/issues
Keywords: file-verifier,file-validator,filetype,magic,mimetypes,puremagic,Pillow
Classifier: Programming Language :: Python :: 3
Classifier: License :: OSI Approved :: MIT License
Classifier: Operating System :: OS Independent
Classifier: Development Status :: 2 - Pre-Alpha
Requires-Python: >=3.10
License-File: LICENSE.txt
Provides-Extra: dev
Requires-Dist: black ; extra == 'dev'
Requires-Dist: flake8 ; extra == 'dev'
Requires-Dist: flake8-pyproject ; extra == 'dev'
Requires-Dist: pytest ; extra == 'dev'
Requires-Dist: typing-extensions ; extra == 'dev'
